friendlyautopep8/.__init__.py.swp
friendlyautopep8/.__init__.py.un~
friendlyautopep8/.__main__.py.un~
friendlyautopep8/__init__.py
friendlyautopep8/__main__.py
friendlyautopep8-0.0.4.dist-info/entry_points.txt
friendlyautopep8-0.0.4.dist-info/WHEEL
friendlyautopep8-0.0.4.dist-info/METADATA
friendlyautopep8-0.0.4.dist-info/RECORD
