Metadata-Version: 1.2
Name: friendlyautopep8
Version: 0.0.4
Summary: Just a wrapper around autopep8 which run _only_ on the changed (non commited
Home-page: https://github.com/Carreau/friendlyautopep8
License: UNKNOWN
Author: Matthias Bussonnier
Author-email: bussonniermatthias@gmail.com
Requires-Python: >=3.4
Classifier: License :: OSI Approved :: MIT License
Requires-Dist: autopep8
